agentscope_runtime/__init__.py
agentscope_runtime/version.py
agentscope_runtime/adapters/__init__.py
agentscope_runtime/adapters/utils.py
agentscope_runtime/adapters/agentscope/__init__.py
agentscope_runtime/adapters/agentscope/message.py
agentscope_runtime/adapters/agentscope/stream.py
agentscope_runtime/adapters/agentscope/long_term_memory/__init__.py
agentscope_runtime/adapters/agentscope/long_term_memory/_long_term_memory_adapter.py
agentscope_runtime/adapters/agentscope/memory/__init__.py
agentscope_runtime/adapters/agentscope/memory/_memory_adapter.py
agentscope_runtime/adapters/agentscope/tool/__init__.py
agentscope_runtime/adapters/agentscope/tool/sandbox_tool.py
agentscope_runtime/adapters/agentscope/tool/tool.py
agentscope_runtime/adapters/agno/__init__.py
agentscope_runtime/adapters/agno/message.py
agentscope_runtime/adapters/agno/stream.py
agentscope_runtime/adapters/autogen/__init__.py
agentscope_runtime/adapters/autogen/tool/__init__.py
agentscope_runtime/adapters/autogen/tool/tool.py
agentscope_runtime/adapters/langgraph/__init__.py
agentscope_runtime/adapters/langgraph/message.py
agentscope_runtime/adapters/langgraph/stream.py
agentscope_runtime/adapters/ms_agent_framework/__init__.py
agentscope_runtime/adapters/ms_agent_framework/message.py
agentscope_runtime/adapters/ms_agent_framework/stream.py
agentscope_runtime/adapters/text/__init__.py
agentscope_runtime/adapters/text/stream.py
agentscope_runtime/cli/__init__.py
agentscope_runtime/cli/cli.py
agentscope_runtime/cli/commands/__init__.py
agentscope_runtime/cli/commands/chat.py
agentscope_runtime/cli/commands/deploy.py
agentscope_runtime/cli/commands/invoke.py
agentscope_runtime/cli/commands/list_cmd.py
agentscope_runtime/cli/commands/run.py
agentscope_runtime/cli/commands/sandbox.py
agentscope_runtime/cli/commands/status.py
agentscope_runtime/cli/commands/stop.py
agentscope_runtime/cli/commands/web.py
agentscope_runtime/cli/loaders/__init__.py
agentscope_runtime/cli/loaders/agent_loader.py
agentscope_runtime-1.0.5.post1.dist-info/licenses/LICENSE
agentscope_runtime-1.0.5.post1.dist-info/METADATA
agentscope_runtime-1.0.5.post1.dist-info/WHEEL
agentscope_runtime-1.0.5.post1.dist-info/entry_points.txt
agentscope_runtime-1.0.5.post1.dist-info/top_level.txt
agentscope_runtime-1.0.5.post1.dist-info/RECORD
