Metadata-Version: 2.4
Name: agentscope-runtime
Version: 1.0.5.post1
Summary: A production-ready runtime framework for agent applications, providing secure sandboxed execution environments and scalable deployment solutions with multi-framework support.
Requires-Python: >=3.10
License-File: LICENSE
Requires-Dist: mcp>=1.13
Requires-Dist: fastapi>=0.104.0
Requires-Dist: uvicorn[standard]>=0.24.0
Requires-Dist: openai
Requires-Dist: pydantic>=2.11.7
Requires-Dist: requests>=2.32.4
Requires-Dist: agentscope<1.0.12,>=1.0.9
Requires-Dist: docker>=7.1.0
Requires-Dist: redis>=6.0.0
Requires-Dist: oss2>=2.19.1
Requires-Dist: pydantic-settings>=2.9.1
Requires-Dist: python-dotenv>=1.0.1
Requires-Dist: kubernetes>=33.1.0
Requires-Dist: shortuuid>=1.0.13
Requires-Dist: celery[redis]>=5.3.1
Requires-Dist: a2a-sdk>=0.3.0
Requires-Dist: jinja2
Requires-Dist: psutil
Requires-Dist: dashscope>=1.25.0
Requires-Dist: jsonref
Requires-Dist: asgiref
Requires-Dist: click>=8.0.0
Requires-Dist: rich>=13.0.0
Requires-Dist: ag-ui-protocol>=0.1.10
Provides-Extra: dev
Requires-Dist: pytest>=8.3.5; extra == "dev"
Requires-Dist: pytest-asyncio>=0.23.0; extra == "dev"
Requires-Dist: pre-commit>=4.2.0; extra == "dev"
Requires-Dist: jupyter-book<2.0.0,>=1.0.4.post1; extra == "dev"
Requires-Dist: furo>=2025.7.19; extra == "dev"
Requires-Dist: pytest-cov>=6.2.1; extra == "dev"
Requires-Dist: fakeredis>=2.31.0; extra == "dev"
Requires-Dist: sphinx-autoapi>=3.6.0; extra == "dev"
Requires-Dist: pytest-mock>=3.15.1; extra == "dev"
Requires-Dist: sphinxcontrib-mermaid>=1.2.3; extra == "dev"
Provides-Extra: ext
Requires-Dist: langchain>=1.1.3; extra == "ext"
Requires-Dist: langchain_openai>=1.0.1; extra == "ext"
Requires-Dist: langgraph>=1.0.4; extra == "ext"
Requires-Dist: autogen-agentchat>=0.7.0; extra == "ext"
Requires-Dist: reme-ai>=0.2.0.2; extra == "ext"
Requires-Dist: mem0ai>=0.1.117; extra == "ext"
Requires-Dist: alibabacloud-agentrun20250910>=2.0.1; extra == "ext"
Requires-Dist: alibabacloud_tea_openapi>=0.4.0; extra == "ext"
Requires-Dist: alibabacloud-fc20230330>=4.4.0; extra == "ext"
Requires-Dist: tablestore-for-agent-memory>=1.1.0; extra == "ext"
Requires-Dist: langchain-community>=0.3.27; extra == "ext"
Requires-Dist: wuying-agentbay-sdk<0.13.0,>=0.5.0; extra == "ext"
Requires-Dist: alipay-sdk-python; extra == "ext"
Requires-Dist: cryptography; extra == "ext"
Requires-Dist: gunicorn>=20.0.0; extra == "ext"
Requires-Dist: starlette>=0.37.0; extra == "ext"
Requires-Dist: asgiref>=3.11.0; extra == "ext"
Requires-Dist: azure-cognitiveservices-speech>=1.47.0; extra == "ext"
Requires-Dist: alibabacloud-oss-v2; extra == "ext"
Requires-Dist: alibabacloud-bailian20231229>=2.6.0; extra == "ext"
Requires-Dist: build; extra == "ext"
Requires-Dist: setuptools>=40.8.0; extra == "ext"
Requires-Dist: wheel; extra == "ext"
Requires-Dist: alibabacloud-credentials; extra == "ext"
Requires-Dist: PyYAML; extra == "ext"
Requires-Dist: agno>=2.3.8; extra == "ext"
Requires-Dist: nacos-sdk-python>=3.0.0; extra == "ext"
Requires-Dist: agent-framework<1.0.0b260114,>=1.0.0b251120; extra == "ext"
Requires-Dist: boxlite>=0.5.2; extra == "ext"
Requires-Dist: alibabacloud-eas20210701<8.0.0,>=7.0.0; extra == "ext"
Requires-Dist: alibabacloud-aiworkspace20210204<8.0.0,>=7.0.0; extra == "ext"
Dynamic: license-file
